divengine/pyvault/__init__.py
divengine/pyvault/core.py
divengine_pyvault-1.0.3.dist-info/licenses/LICENSE
divengine_pyvault-1.0.3.dist-info/METADATA
divengine_pyvault-1.0.3.dist-info/WHEEL
divengine_pyvault-1.0.3.dist-info/entry_points.txt
divengine_pyvault-1.0.3.dist-info/top_level.txt
divengine_pyvault-1.0.3.dist-info/RECORD
