Metadata-Version: 2.4
Name: divengine-pyvault
Version: 1.0.3
Summary: Divengine Python Vault – Generates Obsidian vaults from Python projects
Author-email: Rafael Rodriguez Ramirez <rafageist@divengine.com>
License: MIT
Project-URL: Homepage, https://github.com/divengine/pyvault
Project-URL: Repository, https://github.com/divengine/pyvault
Requires-Python: >=3.9
License-File: LICENSE
Dynamic: license-file
